varibayes/__init__.py
varibayes/infer.py
varibayes/opt/__init__.py
varibayes/opt/adadelta.py
varibayes/opt/adam.py
varibayes/tests/__init__.py
varibayes/tests/gradient.py
varibayes/tests/polyfit.py
varibayes-0.0.1.dist-info/DESCRIPTION.rst
varibayes-0.0.1.dist-info/METADATA
varibayes-0.0.1.dist-info/RECORD
varibayes-0.0.1.dist-info/WHEEL
varibayes-0.0.1.dist-info/metadata.json
varibayes-0.0.1.dist-info/top_level.txt
